LICENSE
MANIFEST.in
README.md
setup.py
pyexamgrading/Exam.py
pyexamgrading/ExamResults.py
pyexamgrading/Exceptions.py
pyexamgrading/FriendlyArgumentParser.py
pyexamgrading/GradingScheme.py
pyexamgrading/MoodleCSV.py
pyexamgrading/MultiCommand.py
pyexamgrading/PrefixMatcher.py
pyexamgrading/Structure.py
pyexamgrading/Student.py
pyexamgrading/Tools.py
pyexamgrading/WorkDir.py
pyexamgrading/__init__.py
pyexamgrading/__main__.py
pyexamgrading.egg-info/PKG-INFO
pyexamgrading.egg-info/SOURCES.txt
pyexamgrading.egg-info/dependency_links.txt
pyexamgrading.egg-info/entry_points.txt
pyexamgrading.egg-info/requires.txt
pyexamgrading.egg-info/top_level.txt
pyexamgrading/actions/ActionEnterResults.py
pyexamgrading/actions/ActionExport.py
pyexamgrading/actions/ActionImport.py
pyexamgrading/actions/ActionNewExam.py
pyexamgrading/actions/ActionPrint.py
pyexamgrading/actions/__init__.py
pyexamgrading/templates/export.tex