Metadata-Version: 2.1
Name: pyexamgrading
Version: 0.0.1
Summary: Manage grade computation of university exams
Home-page: https://github.com/johndoe31415/pyexamgrading
Download-URL: https://github.com/johndoe31415/pyexamgrading/archive/0.0.1.tar.gz
Author: Johannes Bauer
Author-email: joe@johannes-bauer.com
License: gpl-3.0
Keywords: python,exam,university
Classifier: Development Status :: 5 - Production/Stable
Classifier: Intended Audience :: Developers
Classifier: License :: OSI Approved :: GNU General Public License v3 (GPLv3)
Classifier: Programming Language :: Python :: 3
Classifier: Programming Language :: Python :: 3 :: Only
Classifier: Programming Language :: Python :: 3.12
License-File: LICENSE
Requires-Dist: mako
